dnr/NewsRecommender.py
dnr-0.9.3.dist-info/DESCRIPTION.rst
dnr-0.9.3.dist-info/METADATA
dnr-0.9.3.dist-info/RECORD
dnr-0.9.3.dist-info/WHEEL
dnr-0.9.3.dist-info/metadata.json
dnr-0.9.3.dist-info/top_level.txt
